pc/__init__.py
pc/_funcs_/__init__.py
pc/_funcs_/code.py
pc/_funcs_/color_log.py
pc/_funcs_/db_func.py
pc/_funcs_/helps.py
pc/_funcs_/parser.py
pc/_funcs_/string_func.py
pc/_funcs_/text_parser.py
pc/_funcs_/__pycache__/__init__.cpython-37.pyc
pc/_funcs_/__pycache__/code.cpython-37.pyc
pc/_funcs_/__pycache__/color_log.cpython-37.pyc
pc/_funcs_/__pycache__/db_func.cpython-37.pyc
pc/_funcs_/__pycache__/helps.cpython-37.pyc
pc/_funcs_/__pycache__/parser.cpython-37.pyc
pc/_funcs_/__pycache__/string_func.cpython-37.pyc
pc/file_funcs/__init__.py
pc/file_funcs/file_eval.py
pc/file_funcs/get_file.py
pc/file_funcs/__pycache__/__init__.cpython-37.pyc
pc/file_funcs/__pycache__/file_eval.cpython-37.pyc
pc/file_funcs/__pycache__/get_file.cpython-37.pyc
pc/maths/__init__.py
pc/maths/array.py
pc/maths/matrix.py
pc/maths/pythagores.py
pc/maths/shape.py
pc/maths/simple_math.py
pc/maths/__pycache__/__init__.cpython-37.pyc
pc/maths/__pycache__/matrix.cpython-37.pyc
pc/maths/__pycache__/pythagores.cpython-37.pyc
pc/maths/__pycache__/shape.cpython-37.pyc
pc/maths/__pycache__/simple_math.cpython-37.pyc
pycosmic-4.1.1.dist-info/METADATA
pycosmic-4.1.1.dist-info/WHEEL
pycosmic-4.1.1.dist-info/top_level.txt
pycosmic-4.1.1.dist-info/RECORD
