Metadata-Version: 2.1
Name: pycosmic
Version: 4.1.1
Summary: Packages That has Many Useful Code   
Home-page: UNKNOWN
Author: Rishabh
Author-email: rishivisionworld@gmail.com
License: UNKNOWN
Platform: UNKNOWN
Requires-Dist: colorama
